simple_add_tesfahiwet/__init__.py
simple_add_tesfahiwet/add.py
simple_add_tesfahiwet-0.1.1.dist-info/METADATA
simple_add_tesfahiwet-0.1.1.dist-info/WHEEL
simple_add_tesfahiwet-0.1.1.dist-info/top_level.txt
simple_add_tesfahiwet-0.1.1.dist-info/RECORD
