Metadata-Version: 2.4
Name: simple_add_tesfahiwet
Version: 0.1.1
Summary: A simple example package that adds two numbers.
Author: Tesfahiwet Yemane
Author-email: Tesfahiwet Yemane <tesfahiwetgeol@gmail.com>
License: MIT
Requires-Python: >=3.7
